[
  {
    "elements": [
      {
        "id": "as-an-user-i-want-to-view-the-most-popular-tv-shows-so-that-i-can-see-what-tv-shows-are-popular.;open-menu.",
        "keyword": "Scenario",
        "line": 3,
        "name": "Open menu.",
        "steps": [
          {
            "arguments": [],
            "keyword": "Given ",
            "name": "that I am on the IMDB site.",
            "result": {
              "status": "undefined"
            },
            "line": 4
          },
          {
            "arguments": [],
            "keyword": "When ",
            "name": "I click on the Menu button.",
            "result": {
              "status": "undefined"
            },
            "line": 5
          },
          {
            "arguments": [],
            "keyword": "Then ",
            "name": "I would like to see the menu of what IMDB has to offer.",
            "result": {
              "status": "undefined"
            },
            "line": 6
          },
          {
            "arguments": [],
            "keyword": "After ",
            "result": {
              "status": "passed",
              "duration": 6090489800
            },
            "hidden": true,
            "match": {
              "location": "C:\\Users\\LadyQuinn\\Desktop\\testporjekt\\IJJO\\node_modules\\selenium-cucumber-js\\runtime\\world.js:250"
            }
          }
        ],
        "tags": [],
        "type": "scenario"
      },
      {
        "id": "as-an-user-i-want-to-view-the-most-popular-tv-shows-so-that-i-can-see-what-tv-shows-are-popular.;view-a-list-of-the-most-popular-shows.",
        "keyword": "Scenario",
        "line": 8,
        "name": "View a list of the Most popular shows.",
        "steps": [
          {
            "arguments": [],
            "keyword": "Given ",
            "name": "that I am on the IMDB site.",
            "result": {
              "status": "undefined"
            },
            "line": 9
          },
          {
            "arguments": [],
            "keyword": "When ",
            "name": "I click on the text ”Most popular TV shows”.",
            "result": {
              "status": "undefined"
            },
            "line": 10
          },
          {
            "arguments": [],
            "keyword": "Then ",
            "name": "I should see a list of the Most popular TV shows.",
            "result": {
              "status": "undefined"
            },
            "line": 11
          },
          {
            "arguments": [],
            "keyword": "After ",
            "result": {
              "status": "passed",
              "duration": 5722837200
            },
            "hidden": true,
            "match": {
              "location": "C:\\Users\\LadyQuinn\\Desktop\\testporjekt\\IJJO\\node_modules\\selenium-cucumber-js\\runtime\\world.js:250"
            }
          }
        ],
        "tags": [],
        "type": "scenario"
      }
    ],
    "id": "as-an-user-i-want-to-view-the-most-popular-tv-shows-so-that-i-can-see-what-tv-shows-are-popular.",
    "keyword": "Feature",
    "line": 1,
    "name": "As an user I want to view the most popular tv shows so that I can see what tv shows are popular.",
    "tags": [],
    "uri": "C:\\Users\\LadyQuinn\\Desktop\\testporjekt\\IJJO\\features\\most-popular-tv-shows.feature"
  }
]